configISOM2017.csv
map_analyser/__init__.py
map_analyser/__main__.py
map_analyser/app/__init__.py
map_analyser/app/presenters.py
map_analyser/app/util.py
map_analyser/app/write_omap.py
map_analyser/lib/__init__.py
map_analyser/lib/poly_decomp.py
map_analyser/lib/py2D.py
map_analyser/mapanalyser/__init__.py
map_analyser/mapanalyser/algorithm.py
map_analyser/mapanalyser/analyser.py
map_analyser/mapanalyser/clipper.py
map_analyser/mapanalyser/CPsolver.py
map_analyser/mapanalyser/geometry.py
map_analyser/mapanalyser/graph.py
map_analyser/mapanalyser/util.py
map_analyser/maplib/__init__.py
map_analyser/maplib/map.py
map_analyser/maplib/util.py
map_analyser/maplib/xmlmap.py
map_analyser-0.2.1.dist-info/entry_points.txt
map_analyser-0.2.1.dist-info/WHEEL
map_analyser-0.2.1.dist-info/METADATA
map_analyser-0.2.1.dist-info/RECORD
